meteosatpy/__init__.py
meteosatpy/chirps.py
meteosatpy/cmorph.py
meteosatpy/imerg.py
meteosatpy/mswep.py
meteosatpy/persiann.py
meteosatpy/utils.py
meteosatpy/warnings.py
meteosatpy-0.0.5.dist-info/LICENCE.txt
meteosatpy-0.0.5.dist-info/METADATA
meteosatpy-0.0.5.dist-info/WHEEL
meteosatpy-0.0.5.dist-info/top_level.txt
meteosatpy-0.0.5.dist-info/RECORD
