Metadata-Version: 2.1
Name: meteosatpy
Version: 0.0.5
Summary: Library designed for downloading and managing meteorological data sourced from satellites and global models.
Home-page: https://github.com/jusethCS/meteosatpy
Author: Juseth Enrique Chancay Sánchez
Author-email: juseth.chancay@gmail.com
License: MIT
License-File: LICENCE.txt
Requires-Dist: rasterio
Requires-Dist: xarray
Requires-Dist: geopandas
Requires-Dist: requests
